auto_dl/Automater.py
auto_dl/__init__.py
auto_dl/lib.py
auto_dl-0.1.1.dist-info/METADATA
auto_dl-0.1.1.dist-info/RECORD
auto_dl-0.1.1.dist-info/WHEEL
auto_dl-0.1.1.dist-info/top_level.txt
