Metadata-Version: 2.1
Name: auto-dl
Version: 0.1.1
Summary: test
Home-page: https://github.com/bjherger/auto_dl
Author: Brendan Herger
Author-email: 13herger@gmail.com
License: MIT
Platform: UNKNOWN
Requires-Dist: Keras (==2.1.5)
Requires-Dist: numpy (==1.14.2)
Requires-Dist: pandas (==0.22.0)
Requires-Dist: pip (==9.0.3)
Requires-Dist: python-dateutil (==2.7.2)
Requires-Dist: pytz (==2018.4)
Requires-Dist: PyYAML (==3.12)
Requires-Dist: scikit-learn (==0.19.1)
Requires-Dist: scipy (==1.0.1)
Requires-Dist: setuptools (==39.0.1)
Requires-Dist: six (==1.11.0)
Requires-Dist: sklearn (==0.0)
Requires-Dist: sklearn-pandas (==1.6.0)
Requires-Dist: wheel (==0.31.0)
